nnl/__init__.py
nnl/cli.py
nnl/core.py
nnlpy-0.4.0.dist-info/licenses/LICENSE
nnlpy-0.4.0.dist-info/METADATA
nnlpy-0.4.0.dist-info/WHEEL
nnlpy-0.4.0.dist-info/entry_points.txt
nnlpy-0.4.0.dist-info/top_level.txt
nnlpy-0.4.0.dist-info/RECORD
