Metadata-Version: 2.4
Name: nnlpy
Version: 0.4.0
Summary: NNL parser/serializer - Near Natural Language (JSON-capable)
Author: Shivam Kumar
License-Expression: MIT
Requires-Python: >=3.8
License-File: LICENSE
Dynamic: license-file
